threadedsqlite/__init__.py
threadedsqlite/sqlite.py
ThreadedSQLite-0.1.0.dist-info/LICENSE
ThreadedSQLite-0.1.0.dist-info/METADATA
ThreadedSQLite-0.1.0.dist-info/WHEEL
ThreadedSQLite-0.1.0.dist-info/top_level.txt
ThreadedSQLite-0.1.0.dist-info/RECORD
